main.py
setup.py
arjuno/__init__.py
arjuno/bin.py
arjuno/cli.py
arjuno/echo_ser.py
arjuno/main.py
arjuno.egg-info/PKG-INFO
arjuno.egg-info/SOURCES.txt
arjuno.egg-info/dependency_links.txt
arjuno.egg-info/entry_points.txt
arjuno.egg-info/requires.txt
arjuno.egg-info/top_level.txt
arjuno.egg-info/zip-safe
arjuno/libs/__init__.py
arjuno/libs/check_serial.py
arjuno/libs/lib_serial.py
arjuno/libs/lib_telegram.py
arjuno/libs/telebot.py