Metadata-Version: 1.1
Name: arjuno
Version: 0.0.1
Summary: serial SDK IOT
Home-page: https://github.com/rendiya/arjuno
Author: rendiya
Author-email: ligerrendy@gmail.com
License: Apache2
Platform: UNKNOWN
Classifier: Development Status :: 1 - Planning
Classifier: Environment :: Console
Classifier: Intended Audience :: Developers
Classifier: License :: OSI Approved :: Apache Software License
Classifier: Operating System :: POSIX :: Linux
Classifier: Programming Language :: Python
Classifier: Programming Language :: Python :: 2
Classifier: Programming Language :: Python :: 2.7
Classifier: Topic :: Communications
Classifier: Topic :: Software Development :: Libraries :: Python Modules
